{
  "generated_at": "2026-04-04T12:39:30.222355+00:00",
  "top_cards": [
    {
      "label": "US stocks tracked",
      "value": 100,
      "detail": "Using public Finviz fallback because NEWSBOT_FMP_API_KEY is not configured. Public Finviz snapshot is capped at the top 100 stocks to avoid rate limits.",
      "status": "ok"
    },
    {
      "label": "Crypto assets tracked",
      "value": 120,
      "detail": "coingecko",
      "status": "ok"
    },
    {
      "label": "Stock advancers",
      "value": 52,
      "detail": "Decliners 48",
      "status": "ok"
    },
    {
      "label": "Crypto advancers",
      "value": 43,
      "detail": "Decliners 73",
      "status": "ok"
    }
  ],
  "status": {
    "generated_at": "2026-04-04T12:39:30.222355+00:00",
    "overall_status": "ok",
    "providers": {
      "stocks": {
        "status": "ok",
        "stale": false,
        "provider": "finviz-public",
        "message": "Using public Finviz fallback because NEWSBOT_FMP_API_KEY is not configured. Public Finviz snapshot is capped at the top 100 stocks to avoid rate limits.",
        "as_of": "2026-04-04T12:39:30.222355+00:00",
        "row_count": 100
      },
      "crypto": {
        "status": "ok",
        "stale": false,
        "provider": "coingecko",
        "message": null,
        "as_of": "2026-04-04T12:39:31.088Z",
        "row_count": 120
      }
    }
  },
  "stocks": {
    "status": "ok",
    "stale": false,
    "message": "Using public Finviz fallback because NEWSBOT_FMP_API_KEY is not configured. Public Finviz snapshot is capped at the top 100 stocks to avoid rate limits.",
    "benchmarks": [
      {
        "asset_type": "stock",
        "symbol": "SPY",
        "name": "SPDR S&P 500 ETF TRUST",
        "exchange": "US",
        "country": "USA",
        "sector_or_category": "Benchmark",
        "industry": "ETF",
        "last": 655.83,
        "change_pct": 0.09,
        "market_cap": null,
        "volume": 67950074.0,
        "avg_volume": 89.53,
        "pe": null,
        "dividend_yield": null,
        "as_of": "2026-04-04T12:39:30.222355+00:00",
        "detail_url": "https://finviz.com/quote.ashx?t=SPY&p=d",
        "high_52w": 697.84,
        "low_52w": 481.8
      },
      {
        "asset_type": "stock",
        "symbol": "QQQ",
        "name": "Invesco QQQ Trust Series 1",
        "exchange": "US",
        "country": "USA",
        "sector_or_category": "Benchmark",
        "industry": "ETF",
        "last": 584.98,
        "change_pct": 0.11,
        "market_cap": null,
        "volume": 50542221.0,
        "avg_volume": 66.15,
        "pe": null,
        "dividend_yield": null,
        "as_of": "2026-04-04T12:39:30.222355+00:00",
        "detail_url": "https://finviz.com/quote.ashx?t=QQQ&p=d",
        "high_52w": 637.01,
        "low_52w": 402.39
      },
      {
        "asset_type": "stock",
        "symbol": "DIA",
        "name": "Spdr Dow Jones Industrial Average ETF Trust",
        "exchange": "US",
        "country": "USA",
        "sector_or_category": "Benchmark",
        "industry": "ETF",
        "last": 465.06,
        "change_pct": -0.09,
        "market_cap": null,
        "volume": 3804420.0,
        "avg_volume": 7.27,
        "pe": null,
        "dividend_yield": null,
        "as_of": "2026-04-04T12:39:30.222355+00:00",
        "detail_url": "https://finviz.com/quote.ashx?t=DIA&p=d",
        "high_52w": 505.3,
        "low_52w": 366.32
      },
      {
        "asset_type": "stock",
        "symbol": "IWM",
        "name": "iShares Russell 2000 ETF",
        "exchange": "US",
        "country": "USA",
        "sector_or_category": "Benchmark",
        "industry": "ETF",
        "last": 251.29,
        "change_pct": 0.69,
        "market_cap": null,
        "volume": 30169638.0,
        "avg_volume": 45.09,
        "pe": null,
        "dividend_yield": null,
        "as_of": "2026-04-04T12:39:30.222355+00:00",
        "detail_url": "https://finviz.com/quote.ashx?t=IWM&p=d",
        "high_52w": 271.6,
        "low_52w": 171.73
      }
    ],
    "breadth": {
      "advancers": 52,
      "decliners": 48,
      "unchanged": 0,
      "new_highs": 0,
      "new_lows": 0
    },
    "top_gainers": [
      {
        "symbol": "INTC",
        "name": "Intel Corp",
        "change_pct": 4.89,
        "last": 50.38,
        "market_cap": 251650000000.0,
        "volume": 116777096.0,
        "detail_url": "https://finviz.com/quote.ashx?t=INTC&p=d"
      },
      {
        "symbol": "AMD",
        "name": "Advanced Micro Devices Inc",
        "change_pct": 3.47,
        "last": 217.5,
        "market_cap": 354610000000.0,
        "volume": 38260180.0,
        "detail_url": "https://finviz.com/quote.ashx?t=AMD&p=d"
      },
      {
        "symbol": "NFLX",
        "name": "Netflix Inc",
        "change_pct": 3.25,
        "last": 98.66,
        "market_cap": 416560000000.0,
        "volume": 36802920.0,
        "detail_url": "https://finviz.com/quote.ashx?t=NFLX&p=d"
      },
      {
        "symbol": "TTE",
        "name": "TotalEnergies SE",
        "change_pct": 2.91,
        "last": 92.39,
        "market_cap": 196300000000.0,
        "volume": 2799719.0,
        "detail_url": "https://finviz.com/quote.ashx?t=TTE&p=d"
      },
      {
        "symbol": "IBM",
        "name": "International Business Machines Corp",
        "change_pct": 2.06,
        "last": 248.16,
        "market_cap": 232780000000.0,
        "volume": 3223365.0,
        "detail_url": "https://finviz.com/quote.ashx?t=IBM&p=d"
      },
      {
        "symbol": "COST",
        "name": "Costco Wholesale Corp",
        "change_pct": 1.85,
        "last": 1014.96,
        "market_cap": 450290000000.0,
        "volume": 1824303.0,
        "detail_url": "https://finviz.com/quote.ashx?t=COST&p=d"
      }
    ],
    "top_losers": [
      {
        "symbol": "TSLA",
        "name": "Tesla Inc",
        "change_pct": -5.42,
        "last": 360.59,
        "market_cap": 1353090000000.0,
        "volume": 82517479.0,
        "detail_url": "https://finviz.com/quote.ashx?t=TSLA&p=d"
      },
      {
        "symbol": "GE",
        "name": "GE Aerospace",
        "change_pct": -3.94,
        "last": 281.16,
        "market_cap": 294880000000.0,
        "volume": 5310111.0,
        "detail_url": "https://finviz.com/quote.ashx?t=GE&p=d"
      },
      {
        "symbol": "ARM",
        "name": "Arm Holdings plc. ADR",
        "change_pct": -3.84,
        "last": 149.11,
        "market_cap": 158350000000.0,
        "volume": 8141912.0,
        "detail_url": "https://finviz.com/quote.ashx?t=ARM&p=d"
      },
      {
        "symbol": "ASML",
        "name": "ASML Holding NV",
        "change_pct": -3.13,
        "last": 1317.23,
        "market_cap": 507690000000.0,
        "volume": 1880920.0,
        "detail_url": "https://finviz.com/quote.ashx?t=ASML&p=d"
      },
      {
        "symbol": "ABBV",
        "name": "Abbvie Inc",
        "change_pct": -2.86,
        "last": 208.84,
        "market_cap": 369260000000.0,
        "volume": 5083736.0,
        "detail_url": "https://finviz.com/quote.ashx?t=ABBV&p=d"
      },
      {
        "symbol": "ISRG",
        "name": "Intuitive Surgical Inc",
        "change_pct": -2.67,
        "last": 452.07,
        "market_cap": 160540000000.0,
        "volume": 1644245.0,
        "detail_url": "https://finviz.com/quote.ashx?t=ISRG&p=d"
      }
    ],
    "most_active": [
      {
        "symbol": "NVDA",
        "name": "NVIDIA Corp",
        "change_pct": 0.93,
        "last": 177.39,
        "market_cap": 4310580000000.0,
        "volume": 141787111.0,
        "detail_url": "https://finviz.com/quote.ashx?t=NVDA&p=d"
      },
      {
        "symbol": "INTC",
        "name": "Intel Corp",
        "change_pct": 4.89,
        "last": 50.38,
        "market_cap": 251650000000.0,
        "volume": 116777096.0,
        "detail_url": "https://finviz.com/quote.ashx?t=INTC&p=d"
      },
      {
        "symbol": "TSLA",
        "name": "Tesla Inc",
        "change_pct": -5.42,
        "last": 360.59,
        "market_cap": 1353090000000.0,
        "volume": 82517479.0,
        "detail_url": "https://finviz.com/quote.ashx?t=TSLA&p=d"
      },
      {
        "symbol": "MU",
        "name": "Micron Technology Inc",
        "change_pct": -0.44,
        "last": 366.24,
        "market_cap": 413020000000.0,
        "volume": 51254239.0,
        "detail_url": "https://finviz.com/quote.ashx?t=MU&p=d"
      },
      {
        "symbol": "AMD",
        "name": "Advanced Micro Devices Inc",
        "change_pct": 3.47,
        "last": 217.5,
        "market_cap": 354610000000.0,
        "volume": 38260180.0,
        "detail_url": "https://finviz.com/quote.ashx?t=AMD&p=d"
      },
      {
        "symbol": "NFLX",
        "name": "Netflix Inc",
        "change_pct": 3.25,
        "last": 98.66,
        "market_cap": 416560000000.0,
        "volume": 36802920.0,
        "detail_url": "https://finviz.com/quote.ashx?t=NFLX&p=d"
      }
    ],
    "group_performance": [
      {
        "label": "Technology",
        "market_cap": 19436340000000.0,
        "count": 27,
        "change_pct": 0.409941084586913
      },
      {
        "label": "Communication Services",
        "market_cap": 9811060000000.0,
        "count": 8,
        "change_pct": -0.26354806718132395
      },
      {
        "label": "Financial",
        "market_cap": 5872270000000.0,
        "count": 18,
        "change_pct": -0.05713800625652431
      },
      {
        "label": "Consumer Cyclical",
        "market_cap": 4736680000000.0,
        "count": 7,
        "change_pct": -2.0167028171630763
      },
      {
        "label": "Healthcare",
        "market_cap": 4166100000000.0,
        "count": 14,
        "change_pct": -0.8244308345935047
      },
      {
        "label": "Consumer Defensive",
        "market_cap": 2576390000000.0,
        "count": 6,
        "change_pct": 0.845617744207981
      },
      {
        "label": "Industrials",
        "market_cap": 2027630000000.0,
        "count": 10,
        "change_pct": -0.5547765617987502
      },
      {
        "label": "Energy",
        "market_cap": 1683960000000.0,
        "count": 5,
        "change_pct": 0.8399982184849997
      }
    ],
    "heatmap": [
      {
        "label": "NVDA",
        "subLabel": "Technology",
        "change_pct": 0.93,
        "value": 4310580000000.0,
        "size": 4,
        "detail_url": "https://finviz.com/quote.ashx?t=NVDA&p=d"
      },
      {
        "label": "AAPL",
        "subLabel": "Technology",
        "change_pct": 0.11,
        "value": 3757200000000.0,
        "size": 4,
        "detail_url": "https://finviz.com/quote.ashx?t=AAPL&p=d"
      },
      {
        "label": "GOOGL",
        "subLabel": "Communication Services",
        "change_pct": -0.54,
        "value": 3570810000000.0,
        "size": 4,
        "detail_url": "https://finviz.com/quote.ashx?t=GOOGL&p=d"
      },
      {
        "label": "GOOG",
        "subLabel": "Communication Services",
        "change_pct": -0.15,
        "value": 3570810000000.0,
        "size": 4,
        "detail_url": "https://finviz.com/quote.ashx?t=GOOG&p=d"
      },
      {
        "label": "MSFT",
        "subLabel": "Technology",
        "change_pct": 1.11,
        "value": 2773180000000.0,
        "size": 3,
        "detail_url": "https://finviz.com/quote.ashx?t=MSFT&p=d"
      },
      {
        "label": "AMZN",
        "subLabel": "Consumer Cyclical",
        "change_pct": -0.38,
        "value": 2251860000000.0,
        "size": 3,
        "detail_url": "https://finviz.com/quote.ashx?t=AMZN&p=d"
      },
      {
        "label": "TSM",
        "subLabel": "Technology",
        "change_pct": -0.72,
        "value": 1758430000000.0,
        "size": 2,
        "detail_url": "https://finviz.com/quote.ashx?t=TSM&p=d"
      },
      {
        "label": "AVGO",
        "subLabel": "Technology",
        "change_pct": 0.34,
        "value": 1489290000000.0,
        "size": 2,
        "detail_url": "https://finviz.com/quote.ashx?t=AVGO&p=d"
      },
      {
        "label": "META",
        "subLabel": "Communication Services",
        "change_pct": -0.82,
        "value": 1453130000000.0,
        "size": 2,
        "detail_url": "https://finviz.com/quote.ashx?t=META&p=d"
      },
      {
        "label": "TSLA",
        "subLabel": "Consumer Cyclical",
        "change_pct": -5.42,
        "value": 1353090000000.0,
        "size": 2,
        "detail_url": "https://finviz.com/quote.ashx?t=TSLA&p=d"
      },
      {
        "label": "BRK-B",
        "subLabel": "Financial",
        "change_pct": -0.24,
        "value": 1029190000000.0,
        "size": 1,
        "detail_url": "https://finviz.com/quote.ashx?t=BRK-B&p=d"
      },
      {
        "label": "WMT",
        "subLabel": "Consumer Defensive",
        "change_pct": 0.84,
        "value": 1002850000000.0,
        "size": 1,
        "detail_url": "https://finviz.com/quote.ashx?t=WMT&p=d"
      },
      {
        "label": "LLY",
        "subLabel": "Healthcare",
        "change_pct": -1.98,
        "value": 883950000000.0,
        "size": 1,
        "detail_url": "https://finviz.com/quote.ashx?t=LLY&p=d"
      },
      {
        "label": "JPM",
        "subLabel": "Financial",
        "change_pct": -0.26,
        "value": 794550000000.0,
        "size": 1,
        "detail_url": "https://finviz.com/quote.ashx?t=JPM&p=d"
      },
      {
        "label": "XOM",
        "subLabel": "Energy",
        "change_pct": -0.06,
        "value": 669560000000.0,
        "size": 1,
        "detail_url": "https://finviz.com/quote.ashx?t=XOM&p=d"
      },
      {
        "label": "JNJ",
        "subLabel": "Healthcare",
        "change_pct": -0.44,
        "value": 585390000000.0,
        "size": 1,
        "detail_url": "https://finviz.com/quote.ashx?t=JNJ&p=d"
      },
      {
        "label": "V",
        "subLabel": "Financial",
        "change_pct": 0.77,
        "value": 573330000000.0,
        "size": 1,
        "detail_url": "https://finviz.com/quote.ashx?t=V&p=d"
      },
      {
        "label": "ASML",
        "subLabel": "Technology",
        "change_pct": -3.13,
        "value": 507690000000.0,
        "size": 1,
        "detail_url": "https://finviz.com/quote.ashx?t=ASML&p=d"
      },
      {
        "label": "COST",
        "subLabel": "Consumer Defensive",
        "change_pct": 1.85,
        "value": 450290000000.0,
        "size": 1,
        "detail_url": "https://finviz.com/quote.ashx?t=COST&p=d"
      },
      {
        "label": "MA",
        "subLabel": "Financial",
        "change_pct": 0.36,
        "value": 440060000000.0,
        "size": 1,
        "detail_url": "https://finviz.com/quote.ashx?t=MA&p=d"
      },
      {
        "label": "ORCL",
        "subLabel": "Technology",
        "change_pct": 0.79,
        "value": 421000000000.0,
        "size": 1,
        "detail_url": "https://finviz.com/quote.ashx?t=ORCL&p=d"
      },
      {
        "label": "NFLX",
        "subLabel": "Communication Services",
        "change_pct": 3.25,
        "value": 416560000000.0,
        "size": 1,
        "detail_url": "https://finviz.com/quote.ashx?t=NFLX&p=d"
      },
      {
        "label": "MU",
        "subLabel": "Technology",
        "change_pct": -0.44,
        "value": 413020000000.0,
        "size": 1,
        "detail_url": "https://finviz.com/quote.ashx?t=MU&p=d"
      },
      {
        "label": "CVX",
        "subLabel": "Energy",
        "change_pct": 0.79,
        "value": 397020000000.0,
        "size": 1,
        "detail_url": "https://finviz.com/quote.ashx?t=CVX&p=d"
      }
    ]
  },
  "crypto": {
    "status": "ok",
    "stale": false,
    "message": null,
    "benchmarks": [
      {
        "asset_type": "crypto",
        "symbol": "BTC",
        "name": "Bitcoin",
        "exchange": "CoinGecko",
        "country": "Global",
        "sector_or_category": "",
        "industry": "Crypto",
        "last": 67085.0,
        "change_pct": 0.38169,
        "market_cap": 1342545378838.0,
        "volume": 20967508035.0,
        "avg_volume": null,
        "pe": null,
        "dividend_yield": null,
        "as_of": "2026-04-04T12:39:20.472Z",
        "detail_url": "https://www.coingecko.com/en/coins/bitcoin",
        "high_52w": 67171.0,
        "low_52w": 66559.0
      },
      {
        "asset_type": "crypto",
        "symbol": "ETH",
        "name": "Ethereum",
        "exchange": "CoinGecko",
        "country": "Global",
        "sector_or_category": "",
        "industry": "Crypto",
        "last": 2050.58,
        "change_pct": -0.35465,
        "market_cap": 247511004776.0,
        "volume": 5570700821.0,
        "avg_volume": null,
        "pe": null,
        "dividend_yield": null,
        "as_of": "2026-04-04T12:39:20.543Z",
        "detail_url": "https://www.coingecko.com/en/coins/ethereum",
        "high_52w": 2058.39,
        "low_52w": 2044.16
      },
      {
        "asset_type": "crypto",
        "symbol": "XRP",
        "name": "XRP",
        "exchange": "CoinGecko",
        "country": "Global",
        "sector_or_category": "",
        "industry": "Crypto",
        "last": 1.31,
        "change_pct": -1.09907,
        "market_cap": 80490828848.0,
        "volume": 873188741.0,
        "avg_volume": null,
        "pe": null,
        "dividend_yield": null,
        "as_of": "2026-04-04T12:39:30.459Z",
        "detail_url": "https://www.coingecko.com/en/coins/ripple",
        "high_52w": 1.32,
        "low_52w": 1.31
      },
      {
        "asset_type": "crypto",
        "symbol": "SOL",
        "name": "Solana",
        "exchange": "CoinGecko",
        "country": "Global",
        "sector_or_category": "",
        "industry": "Crypto",
        "last": 80.19,
        "change_pct": 0.37884,
        "market_cap": 45939543628.0,
        "volume": 1668901894.0,
        "avg_volume": null,
        "pe": null,
        "dividend_yield": null,
        "as_of": "2026-04-04T12:39:30.411Z",
        "detail_url": "https://www.coingecko.com/en/coins/solana",
        "high_52w": 80.54,
        "low_52w": 79.26
      }
    ],
    "breadth": {
      "advancers": 43,
      "decliners": 73,
      "unchanged": 4,
      "new_highs": 56,
      "new_lows": 54
    },
    "top_gainers": [
      {
        "symbol": "DEXE",
        "name": "DeXe",
        "change_pct": 9.02552,
        "last": 8.8,
        "market_cap": 411682422.0,
        "volume": 13668838.0,
        "detail_url": "https://www.coingecko.com/en/coins/dexe"
      },
      {
        "symbol": "VET",
        "name": "VeChain",
        "change_pct": 8.48049,
        "last": 0.00757928,
        "market_cap": 651822997.0,
        "volume": 33695036.0,
        "detail_url": "https://www.coingecko.com/en/coins/vechain"
      },
      {
        "symbol": "ETC",
        "name": "Ethereum Classic",
        "change_pct": 5.46754,
        "last": 8.46,
        "market_cap": 1320554392.0,
        "volume": 41617831.0,
        "detail_url": "https://www.coingecko.com/en/coins/ethereum-classic"
      },
      {
        "symbol": "ALGO",
        "name": "Algorand",
        "change_pct": 5.13503,
        "last": 0.124557,
        "market_cap": 1106462793.0,
        "volume": 148571108.0,
        "detail_url": "https://www.coingecko.com/en/coins/algorand"
      },
      {
        "symbol": "CAKE",
        "name": "PancakeSwap",
        "change_pct": 4.94901,
        "last": 1.41,
        "market_cap": 482491416.0,
        "volume": 28074236.0,
        "detail_url": "https://www.coingecko.com/en/coins/pancakeswap-token"
      },
      {
        "symbol": "HASH",
        "name": "Provenance Blockchain",
        "change_pct": 3.73036,
        "last": 0.0110262,
        "market_cap": 622502503.0,
        "volume": 4485.11,
        "detail_url": "https://www.coingecko.com/en/coins/hash-2"
      }
    ],
    "top_losers": [
      {
        "symbol": "NIGHT",
        "name": "Midnight",
        "change_pct": -5.06846,
        "last": 0.04200755,
        "market_cap": 698156705.0,
        "volume": 68437031.0,
        "detail_url": "https://www.coingecko.com/en/coins/midnight-3"
      },
      {
        "symbol": "STABLE",
        "name": "​​Stable",
        "change_pct": -3.96758,
        "last": 0.02698317,
        "market_cap": 579471085.0,
        "volume": 16882711.0,
        "detail_url": "https://www.coingecko.com/en/coins/stable-2"
      },
      {
        "symbol": "QNT",
        "name": "Quant",
        "change_pct": -3.27075,
        "last": 73.93,
        "market_cap": 1074492284.0,
        "volume": 12717203.0,
        "detail_url": "https://www.coingecko.com/en/coins/quant-network"
      },
      {
        "symbol": "XTZ",
        "name": "Tezos",
        "change_pct": -3.22186,
        "last": 0.34249,
        "market_cap": 370106809.0,
        "volume": 10947030.0,
        "detail_url": "https://www.coingecko.com/en/coins/tezos"
      },
      {
        "symbol": "WLD",
        "name": "Worldcoin",
        "change_pct": -3.17937,
        "last": 0.263435,
        "market_cap": 853089493.0,
        "volume": 60033438.0,
        "detail_url": "https://www.coingecko.com/en/coins/worldcoin-wld"
      },
      {
        "symbol": "CC",
        "name": "Canton",
        "change_pct": -2.88526,
        "last": 0.139272,
        "market_cap": 5327040071.0,
        "volume": 4980816.0,
        "detail_url": "https://www.coingecko.com/en/coins/canton-network"
      }
    ],
    "most_active": [
      {
        "symbol": "USDT",
        "name": "Tether",
        "change_pct": -0.00499,
        "last": 0.999887,
        "market_cap": 184144763143.0,
        "volume": 32761428837.0,
        "detail_url": "https://www.coingecko.com/en/coins/tether"
      },
      {
        "symbol": "BTC",
        "name": "Bitcoin",
        "change_pct": 0.38169,
        "last": 67085.0,
        "market_cap": 1342545378838.0,
        "volume": 20967508035.0,
        "detail_url": "https://www.coingecko.com/en/coins/bitcoin"
      },
      {
        "symbol": "ETH",
        "name": "Ethereum",
        "change_pct": -0.35465,
        "last": 2050.58,
        "market_cap": 247511004776.0,
        "volume": 5570700821.0,
        "detail_url": "https://www.coingecko.com/en/coins/ethereum"
      },
      {
        "symbol": "USDC",
        "name": "USDC",
        "change_pct": 0.01475,
        "last": 1.0,
        "market_cap": 77532448757.0,
        "volume": 4469453513.0,
        "detail_url": "https://www.coingecko.com/en/coins/usd-coin"
      },
      {
        "symbol": "SOL",
        "name": "Solana",
        "change_pct": 0.37884,
        "last": 80.19,
        "market_cap": 45939543628.0,
        "volume": 1668901894.0,
        "detail_url": "https://www.coingecko.com/en/coins/solana"
      },
      {
        "symbol": "XRP",
        "name": "XRP",
        "change_pct": -1.09907,
        "last": 1.31,
        "market_cap": 80490828848.0,
        "volume": 873188741.0,
        "detail_url": "https://www.coingecko.com/en/coins/ripple"
      }
    ],
    "group_performance": [
      {
        "label": "Smart Contract Platform",
        "market_cap": 1952575989967.9614,
        "change_pct": 0.3127363677206683,
        "volume": 36644667331.58618
      },
      {
        "label": "Layer 1 (L1)",
        "market_cap": 1921459115941.1123,
        "change_pct": 0.3045049467475455,
        "volume": 34637636352.51995
      },
      {
        "label": "Proof of Work (PoW)",
        "market_cap": 1385462064971.4734,
        "change_pct": 0.29775309075604955,
        "volume": 22505621428.119698
      },
      {
        "label": "World Liberty Financial Portfolio",
        "market_cap": 560207907257.9282,
        "change_pct": 0.0028557388183414454,
        "volume": 45690935037.731186
      },
      {
        "label": "Proof of Stake (PoS)",
        "market_cap": 444970562337.73254,
        "change_pct": 0.40348532993566766,
        "volume": 10628690586.621134
      },
      {
        "label": "Stablecoins",
        "market_cap": 311014920406.7236,
        "change_pct": 0.22750430904040067,
        "volume": 39368239237.98896
      },
      {
        "label": "USD Stablecoin",
        "market_cap": 306053906546.0988,
        "change_pct": 0.2313058324419875,
        "volume": 39465880574.02439
      },
      {
        "label": "Fiat-backed Stablecoin",
        "market_cap": 299749187270.1727,
        "change_pct": 0.21270577168444735,
        "volume": 38482180725.55268
      }
    ],
    "heatmap": [
      {
        "label": "Smart Contract Platform",
        "subLabel": "Category",
        "change_pct": 0.3127363677206683,
        "value": 1952575989967.9614,
        "size": 4,
        "detail_url": "https://www.coingecko.com/en/categories"
      },
      {
        "label": "Layer 1 (L1)",
        "subLabel": "Category",
        "change_pct": 0.3045049467475455,
        "value": 1921459115941.1123,
        "size": 4,
        "detail_url": "https://www.coingecko.com/en/categories"
      },
      {
        "label": "Proof of Work (PoW)",
        "subLabel": "Category",
        "change_pct": 0.29775309075604955,
        "value": 1385462064971.4734,
        "size": 3,
        "detail_url": "https://www.coingecko.com/en/categories"
      },
      {
        "label": "World Liberty Financial Portfolio",
        "subLabel": "Category",
        "change_pct": 0.0028557388183414454,
        "value": 560207907257.9282,
        "size": 2,
        "detail_url": "https://www.coingecko.com/en/categories"
      },
      {
        "label": "Proof of Stake (PoS)",
        "subLabel": "Category",
        "change_pct": 0.40348532993566766,
        "value": 444970562337.73254,
        "size": 1,
        "detail_url": "https://www.coingecko.com/en/categories"
      },
      {
        "label": "Stablecoins",
        "subLabel": "Category",
        "change_pct": 0.22750430904040067,
        "value": 311014920406.7236,
        "size": 1,
        "detail_url": "https://www.coingecko.com/en/categories"
      },
      {
        "label": "USD Stablecoin",
        "subLabel": "Category",
        "change_pct": 0.2313058324419875,
        "value": 306053906546.0988,
        "size": 1,
        "detail_url": "https://www.coingecko.com/en/categories"
      },
      {
        "label": "Fiat-backed Stablecoin",
        "subLabel": "Category",
        "change_pct": 0.21270577168444735,
        "value": 299749187270.1727,
        "size": 1,
        "detail_url": "https://www.coingecko.com/en/categories"
      },
      {
        "label": "Made in USA",
        "subLabel": "Category",
        "change_pct": 0.5156329233179805,
        "value": 294572651185.251,
        "size": 1,
        "detail_url": "https://www.coingecko.com/en/categories"
      },
      {
        "label": "Exchange-based Tokens",
        "subLabel": "Category",
        "change_pct": 0.8830830461007028,
        "value": 129910727245.46356,
        "size": 1,
        "detail_url": "https://www.coingecko.com/en/categories"
      },
      {
        "label": "Made in China",
        "subLabel": "Category",
        "change_pct": 1.25866725562275,
        "value": 122958642893.7336,
        "size": 1,
        "detail_url": "https://www.coingecko.com/en/categories"
      },
      {
        "label": "Alleged SEC Securities",
        "subLabel": "Category",
        "change_pct": 1.0281100040860225,
        "value": 120783714470.94626,
        "size": 1,
        "detail_url": "https://www.coingecko.com/en/categories"
      },
      {
        "label": "Base Native",
        "subLabel": "Category",
        "change_pct": 0.6152673609290931,
        "value": 118020536913.47174,
        "size": 1,
        "detail_url": "https://www.coingecko.com/en/categories"
      },
      {
        "label": "Centralized Exchange (CEX) Token",
        "subLabel": "Category",
        "change_pct": 0.8048532266650015,
        "value": 112310259174.62312,
        "size": 1,
        "detail_url": "https://www.coingecko.com/en/categories"
      },
      {
        "label": "MiCA-Compliant Stablecoin",
        "subLabel": "Category",
        "change_pct": 0.4352395703412613,
        "value": 78193533617.97592,
        "size": 1,
        "detail_url": "https://www.coingecko.com/en/categories"
      },
      {
        "label": "Real World Assets (RWA)",
        "subLabel": "Category",
        "change_pct": 0.9324305224705586,
        "value": 54331532854.69214,
        "size": 1,
        "detail_url": "https://www.coingecko.com/en/categories"
      },
      {
        "label": "CoinList Launchpad",
        "subLabel": "Category",
        "change_pct": 1.9919077269265617,
        "value": 53221426175.36639,
        "size": 1,
        "detail_url": "https://www.coingecko.com/en/categories"
      },
      {
        "label": "Decentralized Finance (DeFi)",
        "subLabel": "Category",
        "change_pct": 0.6584248053917791,
        "value": 49397909249.76167,
        "size": 1,
        "detail_url": "https://www.coingecko.com/en/categories"
      },
      {
        "label": "Meme",
        "subLabel": "Category",
        "change_pct": -24.018371341369964,
        "value": 33153640540.37215,
        "size": 1,
        "detail_url": "https://www.coingecko.com/en/categories"
      },
      {
        "label": "Governance",
        "subLabel": "Category",
        "change_pct": 1.1571481095580336,
        "value": 25737042723.472126,
        "size": 1,
        "detail_url": "https://www.coingecko.com/en/categories"
      },
      {
        "label": "Artificial Intelligence (AI)",
        "subLabel": "Category",
        "change_pct": 2.5963175306983604,
        "value": 21401721579.33787,
        "size": 1,
        "detail_url": "https://www.coingecko.com/en/categories"
      },
      {
        "label": "Infrastructure",
        "subLabel": "Category",
        "change_pct": 1.6924827610931434,
        "value": 20751135671.76624,
        "size": 1,
        "detail_url": "https://www.coingecko.com/en/categories"
      },
      {
        "label": "Dog-Themed",
        "subLabel": "Category",
        "change_pct": 0.6602858921156801,
        "value": 18974719438.539375,
        "size": 1,
        "detail_url": "https://www.coingecko.com/en/categories"
      },
      {
        "label": "Privacy",
        "subLabel": "Category",
        "change_pct": 0.22789880921050548,
        "value": 18607092735.432144,
        "size": 1,
        "detail_url": "https://www.coingecko.com/en/categories"
      }
    ],
    "trending": [
      {
        "symbol": "SIREN",
        "name": "Siren",
        "market_cap_rank": 173,
        "detail_url": "https://www.coingecko.com/en/coins/siren-2"
      },
      {
        "symbol": "EDGE",
        "name": "edgeX",
        "market_cap_rank": 119,
        "detail_url": "https://www.coingecko.com/en/coins/edgex"
      },
      {
        "symbol": "HYPE",
        "name": "Hyperliquid",
        "market_cap_rank": 16,
        "detail_url": "https://www.coingecko.com/en/coins/hyperliquid"
      },
      {
        "symbol": "MON",
        "name": "Monad",
        "market_cap_rank": 128,
        "detail_url": "https://www.coingecko.com/en/coins/monad"
      },
      {
        "symbol": "PIPPIN",
        "name": "pippin",
        "market_cap_rank": 530,
        "detail_url": "https://www.coingecko.com/en/coins/pippin"
      },
      {
        "symbol": "BTC",
        "name": "Bitcoin",
        "market_cap_rank": 1,
        "detail_url": "https://www.coingecko.com/en/coins/bitcoin"
      },
      {
        "symbol": "PUFFER",
        "name": "Puffer",
        "market_cap_rank": 936,
        "detail_url": "https://www.coingecko.com/en/coins/puffer"
      },
      {
        "symbol": "SUI",
        "name": "Sui",
        "market_cap_rank": 32,
        "detail_url": "https://www.coingecko.com/en/coins/sui"
      }
    ]
  },
  "market_news": [
    {
      "title": "Easter Candy Sales Decline",
      "source_name": "Bloomberg Markets",
      "canonical_url": "https://www.bloomberg.com/news/videos/2026-04-04/easter-candy-sales-decline-video",
      "published_at": "2026-04-04T12:32:11+00:00",
      "section_label": "시장"
    },
    {
      "title": "Search for Missing US Airman in Iran",
      "source_name": "Bloomberg Markets",
      "canonical_url": "https://www.bloomberg.com/news/videos/2026-04-04/search-for-missing-us-airman-in-iran-video",
      "published_at": "2026-04-04T12:21:51+00:00",
      "section_label": "시장"
    },
    {
      "title": "[디지털투데이] 구글 연구진, 체인별 ‘양자공격’ 취약 구간 정리…비트코인은 송금 중 위험",
      "source_name": "Telegram @dada_news2",
      "canonical_url": "https://www.digitaltoday.co.kr/news/articleView.html?idxno=653620",
      "published_at": "2026-04-04T12:06:50+00:00",
      "section_label": "코인"
    },
    {
      "title": "Solana's quantum-threat readiness reveals harsh tradeoff: security vs speed",
      "source_name": "CoinDesk",
      "canonical_url": "https://www.coindesk.com/tech/2026/04/04/solana-s-quantum-threat-readiness-reveals-harsh-tradeoff-security-vs-speed",
      "published_at": "2026-04-04T12:00:00+00:00",
      "section_label": "코인"
    },
    {
      "title": "Prediction markets are testing legal limits in strict Asian markets",
      "source_name": "Cointelegraph",
      "canonical_url": "https://cointelegraph.com/news/prediction-markets-testing-legal-limits-asia",
      "published_at": "2026-04-04T12:00:00+00:00",
      "section_label": "코인"
    },
    {
      "title": "The US should shape the global climate adaptation market",
      "source_name": "The Hill Feed",
      "canonical_url": "https://thehill.com/opinion/energy-environment/5814681-climate-adaptation-investment-gap",
      "published_at": "2026-04-04T12:00:00+00:00",
      "section_label": "시장"
    },
    {
      "title": "Iran war reality check: Global markets still dictate American energy prices",
      "source_name": "Washington Examiner Feed",
      "canonical_url": "https://www.washingtonexaminer.com/op-eds/4515340/iran-war-global-markets-dictate-american-energy-prices",
      "published_at": "2026-04-04T12:00:00+00:00",
      "section_label": "시장"
    },
    {
      "title": "Bitcoin shorts risk $2.5 billion liquidation at $72K: Are bears in danger?",
      "source_name": "Cointelegraph",
      "canonical_url": "https://cointelegraph.com/news/bitcoin-shorts-risk-2-5-billion-liquidation-72k-are-bears-in-danger",
      "published_at": "2026-04-04T11:58:24+00:00",
      "section_label": "코인"
    },
    {
      "title": "Five data sources say the same thing about bitcoin market. It's thinning from the inside",
      "source_name": "CoinDesk",
      "canonical_url": "https://www.coindesk.com/markets/2026/04/03/five-data-sources-say-the-same-thing-about-bitcoin-market-it-s-thinning-from-the-inside",
      "published_at": "2026-04-04T11:30:00+00:00",
      "section_label": "코인"
    },
    {
      "title": "Politicians want to stop your March Madness predictions",
      "source_name": "Washington Examiner Feed",
      "canonical_url": "https://www.washingtonexaminer.com/op-eds/4513935/politicians-want-to-stop-march-madness-betting-predictions",
      "published_at": "2026-04-04T11:00:00+00:00",
      "section_label": "시장"
    }
  ]
}